zero_point/__init__.py
zero_point/zpt.py
zero_point/coefficients/z5_200720.txt
zero_point/coefficients/z6_200720.txt
gaiadr3_zeropoint-0.1.0.dist-info/LICENSE
gaiadr3_zeropoint-0.1.0.dist-info/METADATA
gaiadr3_zeropoint-0.1.0.dist-info/WHEEL
gaiadr3_zeropoint-0.1.0.dist-info/top_level.txt
gaiadr3_zeropoint-0.1.0.dist-info/RECORD
