Metadata-Version: 2.2
Name: gaiadr3_zeropoint
Version: 0.1.0
Summary: eDR3 zero point functions from Lindegren et al. 2020 implemented in Python.
Home-page: https://gitlab.com/icc-ub/public/gaiadr3_zeropoint
Author: Pau Ramos
Author-email: pau.ramos@nao.ac.jp
License: LGPLv3+
Classifier: Programming Language :: Python :: 3
Classifier: License :: OSI Approved :: GNU Lesser General Public License v3 or later (LGPLv3+)
Classifier: Operating System :: OS Independent
Requires-Python: >=3.6
License-File: LICENSE
Requires-Dist: numpy
Dynamic: author
Dynamic: author-email
Dynamic: classifier
Dynamic: description
Dynamic: description-content-type
Dynamic: home-page
Dynamic: license
Dynamic: requires-dist
Dynamic: requires-python
Dynamic: summary
